librecaptcha/__init__.py
librecaptcha/__main__.py
librecaptcha/cli.py
librecaptcha/errors.py
librecaptcha/extract_strings.py
librecaptcha/gui.py
librecaptcha/librecaptcha.py
librecaptcha/recaptcha.py
librecaptcha/typing.py
librecaptcha/user_agent_data.py
librecaptcha/user_agents.py
librecaptcha-0.7.3.dist-info/LICENSE
librecaptcha-0.7.3.dist-info/METADATA
librecaptcha-0.7.3.dist-info/WHEEL
librecaptcha-0.7.3.dist-info/entry_points.txt
librecaptcha-0.7.3.dist-info/top_level.txt
librecaptcha-0.7.3.dist-info/RECORD
