Metadata-Version: 2.1
Name: librecaptcha
Version: 0.7.3
Summary: A free/libre interface for solving reCAPTCHA challenges.
Home-page: https://github.com/taylordotfish/librecaptcha
Author: taylor.fish
Author-email: contact@taylor.fish
License: GNU General Public License v3 or later (GPLv3+)
Keywords: captcha recaptcha
Platform: UNKNOWN
Classifier: Development Status :: 4 - Beta
Classifier: Topic :: Internet
Classifier: License :: OSI Approved :: GNU General Public License v3 or later (GPLv3+)
Classifier: Operating System :: OS Independent
Classifier: Programming Language :: Python :: 3
Classifier: Programming Language :: Python :: 3.5
Classifier: Programming Language :: Python :: 3.6
Classifier: Programming Language :: Python :: 3.7
Classifier: Programming Language :: Python :: 3.8
Classifier: Programming Language :: Python :: 3.9
Requires-Python: >=3.5
Requires-Dist: Pillow (>=4.1.1)
Requires-Dist: requests (<3,>=2.18.1)
Requires-Dist: esprima (<5,>=4.0.0)
Provides-Extra: gtk
Requires-Dist: PyGObject (<4,>=3.30.0) ; extra == 'gtk'
